async_task_scheduler/__init__.py
async_task_scheduler/py.typed
async_task_scheduler-0.1.1.dist-info/METADATA
async_task_scheduler-0.1.1.dist-info/WHEEL
async_task_scheduler-0.1.1.dist-info/licenses/LICENSE.txt
async_task_scheduler-0.1.1.dist-info/RECORD
