Metadata-Version: 2.4
Name: async_task_scheduler
Version: 0.1.1
Summary: An async task scheduler framework
License: MIT
License-File: LICENSE.txt
Requires-Python: >=3.10
